arbeiter/arbeiter.v
module arbeiter (req_0,req_1,gnt_0,gnt_1,reset,clock);
    input req_0;
    input req_1;
    output gnt_0;
    output gnt_1;
    input reset;
    input clock;

    reg gnt_0;
    reg gnt_1;

    always @ (posedge clock or posedge reset) 
    if(reset) begin
      gnt_0 <= 0;
      gnt_1 <= 0;
    end else if (req_0==1) begin
        gnt_0 <= 1;
        gnt_1 <= 0;
    end else if (req_1==1) begin
        gnt_1 <= 1;
        gnt_0 <= 0;
    end else begin
        gnt_1 <= 0;
        gnt_0 <= 0;
    end

endmodule

2_bit_Arbeiter/arbeiter_tb.v

`include "arbeiter.v"


module arbeiter_tb ();

    reg req_0, req_1, clock, reset;
    wire gnt_0, gnt_1; 

    arbeiter U0 (
        .req_0 (req_0),
        .req_1 (req_1),
        .gnt_0 (gnt_0),
        .gnt_1 (gnt_1),
        .reset (reset),
        .clock (clock)
    );

    initial begin
        clock=0;
        reset=0;
        
        $dumpfile("arbeiter_tb.vcd");
        $dumpvars(0,arbeiter_tb);
        
        reset=0;
        req_0=0;req_1=0;#100;
        req_0=1;req_1=0;#100;
        req_0=0;req_1=1;#100;
        req_0=1;req_1=1;#100;
        req_0=0;req_1=0;#100;

        $finish;

    end

    always begin
       #5 clock = !clock;
    end

endmodule

2_bit_Arbeiter/arbeiter_tb.vcd
$date
	Tue Jan 28 02:11:07 2025
$end
$version
	Icarus Verilog
$end
$timescale
	1s
$end
$scope module arbeiter_tb $end
$var wire 1 ! gnt_1 $end
$var wire 1 " gnt_0 $end
$var reg 1 # clock $end
$var reg 1 $ req_0 $end
$var reg 1 % req_1 $end
$var reg 1 & reset $end
$scope module U0 $end
$var wire 1 # clock $end
$var wire 1 $ req_0 $end
$var wire 1 % req_1 $end
$var wire 1 & reset $end
$var reg 1 " gnt_0 $end
$var reg 1 ! gnt_1 $end
$upscope $end
$upscope $end
$enddefinitions $end
$comment Show the parameter values. $end
$dumpall
$end
#0
$dumpvars
0&
0%
0$
0#
x"
x!
$end
#5
0"
0!
1#
#10
0#
#15
1#
#20
0#
#25
1#
#30
0#
#35
1#
#40
0#
#45
1#
#50
0#
#55
1#
#60
0#
#65
1#
#70
0#
#75
1#
#80
0#
#85
1#
#90
0#
#95
1#
#100
0#
1$
#105
1"
1#
#110
0#
#115
1#
#120
0#
#125
1#
#130
0#
#135
1#
#140
0#
#145
1#
#150
0#
#155
1#
#160
0#
#165
1#
#170
0#
#175
1#
#180
0#
#185
1#
#190
0#
#195
1#
#200
0#
1%
0$
#205
0"
1!
1#
#210
0#
#215
1#
#220
0#
#225
1#
#230
0#
#235
1#
#240
0#
#245
1#
#250
0#
#255
1#
#260
0#
#265
1#
#270
0#
#275
1#
#280
0#
#285
1#
#290
0#
#295
1#
#300
0#
1$
#305
0!
1"
1#
#310
0#
#315
1#
#320
0#
#325
1#
#330
0#
#335
1#
#340
0#
#345
1#
#350
0#
#355
1#
#360
0#
#365
1#
#370
0#
#375
1#
#380
0#
#385
1#
#390
0#
#395
1#
#400
0#
0%
0$
#405
0"
1#
